setup.py
sniffy.py
sniffy.egg-info/PKG-INFO
sniffy.egg-info/SOURCES.txt
sniffy.egg-info/dependency_links.txt
sniffy.egg-info/entry_points.txt
sniffy.egg-info/requires.txt
sniffy.egg-info/top_level.txt