Metadata-Version: 1.0
Name: sniffy
Version: 0.0.1
Summary: Sniffy prints information about captured TCP packages.
Home-page: UNKNOWN
Author: UNKNOWN
Author-email: UNKNOWN
License: UNKNOWN
Keywords: sample setuptools development
Platform: UNKNOWN
